hst_funcs/__init__.py
hst_funcs/duration.py
hst_funcs/ELS/indexing.py
hst_funcs/ELS/xls_split.py
hst_funcs/TF/gpu.py
hst_funcs/finanace/Equity/BS.py
hst_funcs/finanace/Equity/KIBarrier.py
hst_funcs/finanace/Equity/MC_SD.py
hst_funcs/finanace/Equity/MC_vanilla.py
hst_funcs/math/calculus.py
hst_funcs/utils/imsi.py
hst_funcs-1.1.4.dist-info/METADATA
hst_funcs-1.1.4.dist-info/WHEEL
hst_funcs-1.1.4.dist-info/top_level.txt
hst_funcs-1.1.4.dist-info/RECORD
