Metadata-Version: 2.4
Name: hst_funcs
Version: 1.1.4
Summary: My package for practicing to deploy on PyPI.
Author-email: HST <ye0077@naver.com>
Classifier: Programming Language :: Python :: 3
Classifier: License :: OSI Approved :: MIT License
Classifier: Operating System :: OS Independent
Requires-Python: >=3.8
